pysmappee/__init__.py
pysmappee/actuator.py
pysmappee/api.py
pysmappee/appliance.py
pysmappee/config.py
pysmappee/helper.py
pysmappee/measurement.py
pysmappee/mqtt.py
pysmappee/sensor.py
pysmappee/servicelocation.py
pysmappee/smappee.py
pysmappee/smart_device.py
test/__init__.py
pysmappee-0.2.29.dist-info/LICENSE
pysmappee-0.2.29.dist-info/METADATA
pysmappee-0.2.29.dist-info/WHEEL
pysmappee-0.2.29.dist-info/top_level.txt
pysmappee-0.2.29.dist-info/RECORD
