Metadata-Version: 2.1
Name: pysmappee
Version: 0.2.29
Summary: Offical Smappee dev API and MQTT python wrapper
Home-page: https://github.com/smappee/pysmappee
Author: Smappee
Author-email: support@smappee.com
License: MIT
Platform: UNKNOWN
Classifier: Programming Language :: Python :: 3
Classifier: License :: OSI Approved :: MIT License
Classifier: Operating System :: OS Independent
Requires-Python: >=3.7
License-File: LICENSE
